setup.py
django_excel_importer.egg-info/PKG-INFO
django_excel_importer.egg-info/SOURCES.txt
django_excel_importer.egg-info/dependency_links.txt
django_excel_importer.egg-info/requires.txt
django_excel_importer.egg-info/top_level.txt
importer/__init__.py
importer/exception.py
importer/importer.py
importer/serializer.py