Metadata-Version: 2.1
Name: django_excel_importer
Version: 0.1.0
Summary: Django Excel 导入到项目.
Home-page: https://github.com/hubertshelley
Author: Hubert Shelley
Author-email: hubertshelley@163.com
License: MIT
Classifier: License :: OSI Approved :: MIT License
Classifier: Programming Language :: Python
Classifier: Programming Language :: Python :: 3
Classifier: Programming Language :: Python :: 3.7
Classifier: Programming Language :: Python :: Implementation :: CPython
Classifier: Programming Language :: Python :: Implementation :: PyPy
Requires-Python: >=3.7.0
